rule30/__init__.py
rule30/automaton.py
rule30/cli.py
rule30/version.py
rule30/visualize.py
rule30-0.1.dist-info/DESCRIPTION.rst
rule30-0.1.dist-info/METADATA
rule30-0.1.dist-info/RECORD
rule30-0.1.dist-info/WHEEL
rule30-0.1.dist-info/entry_points.txt
rule30-0.1.dist-info/metadata.json
rule30-0.1.dist-info/top_level.txt
